{
    "_meta": {
        "author": "Aryan Naranath 5758224",
        "co_author": "Nael Karimou 5734316",
        "description": "This file contains the data for the rooms in the game. It defines the sprites, their positions, and the walkable area for each room.",
        "todo": "For elenas_room, change 'research_paper' to the actual sprite instead of a ball. Define walkable area for background and positions for sprites. reproduce the same structure others rooms. Adjust if needed. Especially for data collision using depth sorting.",
        "completed": "post_office only"

    },
    "police_station": {
        "objects": ["accusation_board","decor_1","desk","case_file","decor_2","map_board"],
        "detective_rowe": {
            "sprite": "default.png",
            "position": [0.65, 0.3],
            "scale": 0.8
        },
        "background": {
            "path": "background.png",
            "walkable_area": {
                "top_left": [0.04, 0.27],
                "width": 0.97,
                "height": 0.41
            }
        },
        "accusation_board": {
            "path": "accusation_board.png",
            "position": [0.76, 0.2],
            "scale": 0.8,
            "class": "InteractableObject",
            "collision": true
        },
        "case_file": {
            "path": "case_file.png",
            "position": [0.45, 0.34],
            "scale": 0.92,
            "class": "Evidence",
            "collision": false
        },
        "decor_1": {
            "path": "decor_1.png",
            "position": [0.015, 0.42],
            "scale": 0.94,
            "class": "Furniture",
            "collision": true

        },
        "decor_2": {
            "path": "decor_2.png",
            "position": [0.024, 0.086],
            "scale": 0.85,
            "class": "Furniture",
            "collision": true
        },
        "desk": {
            "path": "desk.png",
            "position": [0.35, 0.26],
            "scale": 0.9,
            "class": "Furniture",
            "collision": true
            
        },
        "map_board": {
            "path": "map_board.png",
            "position": [0.67, 0.06],
            "scale": 0.72,
            "class": "InteractableObject",
            "collision": false
        }
    },
    "elenas_office": {
        "room_sprites": ["accusation_board", "background", "bookshelf", "broken_lamp", "chair", "computer", "desk", "dinner_invitation", "research_paper", "tweed_thread"],
        "detective_row_spawn_position": "TODO",
        "detective_row_spawn_sprite": "default.png",
        "background": {
            "path": "background.png",
            "walkable_area": {
                "top_right": "TODO",
                "top_left": "TODO",
                "bottom_right": "TODO",
                "bottom_left": "TODO"
            }
        },
        "board": ["board.png", ["position x", "position y"], "width", "height"],
        "bookshelf": ["bookshelf.png", ["position x", "position y"], "width", "height"],
        "broken_lamp": ["broken_lamp.png", ["position x", "position y"], "width", "height"],
        "chair": ["chair.png", ["position x", "position y"], "width", "height"],
        "computer": ["computer.png", ["position x", "position y"], "width", "height"],
        "desk": ["desk.png", ["position x", "position y"], "width", "height"],
        "dinner_invitation": ["dinner_invitation.png", ["position x", "position y"], "width", "height"],
        "research_paper": ["research_paper.png", ["position x", "position y"], "width", "height"],
        "tweed_thread": ["tweed_thread.png", ["position x", "position y"], "width", "height"]
    }
}